blifparser/__init__.py
blifparser/__main__.py
blifparser/_version.py
blifparser/blifparser.py
blifparser/graph.py
blifparser/utils.py
blifparser/keywords/__init__.py
blifparser/keywords/fsm.py
blifparser/keywords/generic.py
blifparser/keywords/subfiles.py
blifparser-2.0.1.dist-info/LICENSE.txt
blifparser-2.0.1.dist-info/METADATA
blifparser-2.0.1.dist-info/WHEEL
blifparser-2.0.1.dist-info/entry_points.txt
blifparser-2.0.1.dist-info/top_level.txt
blifparser-2.0.1.dist-info/RECORD
