Metadata-Version: 2.1
Name: blifparser
Version: 2.0.1
Summary: A simple BLIF parser
Home-page: https://github.com/mario33881/blifparser
Author: Zenaro Stefano (mario33881)
Author-email: mariortgasd@hotmail.com
License: MIT
Keywords: SIS,BLIF,parser,development
Classifier: Development Status :: 5 - Production/Stable
Classifier: Intended Audience :: Developers
Classifier: Topic :: Software Development
Classifier: Topic :: Software Development :: Libraries :: Python Modules
Classifier: License :: OSI Approved :: MIT License
Classifier: Programming Language :: Python :: 3
Classifier: Operating System :: Unix
Classifier: Operating System :: MacOS :: MacOS X
Classifier: Operating System :: Microsoft :: Windows
Requires-Python: >=3.7
License-File: LICENSE.txt
Requires-Dist: networkx (==2.6.3)
Requires-Dist: matplotlib (==3.5.3)
